autogen/__init__.py
autogen/debug.py
autogen/library/__init__.py
autogen/library/case_select.py
autogen/library/change_terms.py
autogen/library/class_large_operator.py
autogen/library/class_pos.py
autogen/library/class_term.py
autogen/library/compare.py
autogen/library/compare_backup.py
autogen/library/compare_envelope.py
autogen/library/compare_functions.py
autogen/library/compare_functions2.py
autogen/library/compare_level5.py
autogen/library/compare_overall.py
autogen/library/compare_overall2.py
autogen/library/compare_test.py
autogen/library/compare_test_outside.py
autogen/library/convert_pqr.py
autogen/library/eq8.py
autogen/library/eq82.py
autogen/library/full_con.py
autogen/library/function_small.py
autogen/library/functions.py
autogen/library/h_third.py
autogen/library/make_op.py
autogen/library/make_op_Ayush_MBP.py
autogen/library/next_op.py
autogen/library/part_of.py
autogen/library/pick.py
autogen/library/print_op.py
autogen/library/print_terms.py
autogen/library/rn_comm.py
autogen/library/sign_function.py
autogen/library/special_conditions.py
autogen/library/symmetric.py
autogen/main_tools/__init__.py
autogen/main_tools/commutator.py
autogen/main_tools/driv3.py
autogen/main_tools/multi_cont.py
autogen/main_tools/product.py
autogen/pkg/__init__.py
autogen/pkg/ewt.py
autogen/pkg/fewt.py
autogen/pkg/fix_uv.py
autogen/pkg/func_ewt.py
autogen/pkg/make_c.py
autogen/pkg/parity.py
autogen/pkg/returnop.py
autogen_wick-0.1.1.dist-info/licenses/LICENSE
autogen_wick-0.1.1.dist-info/METADATA
autogen_wick-0.1.1.dist-info/WHEEL
autogen_wick-0.1.1.dist-info/top_level.txt
autogen_wick-0.1.1.dist-info/RECORD
