Metadata-Version: 2.4
Name: autogen-wick
Version: 0.1.1
Summary: Automatic Wick's theorem expression generator for quantum chemistry (unitary coupled cluster, CC, etc).
Author: Ayush Asthana
License: MIT
Project-URL: Homepage, https://github.com/asthanaa/autogen
Project-URL: Documentation, https://asthanaa.github.io/autogen/
Classifier: License :: OSI Approved :: MIT License
Classifier: Programming Language :: Python :: 3
Classifier: Programming Language :: Python :: 3.9
Classifier: Programming Language :: Python :: 3.10
Classifier: Programming Language :: Python :: 3.11
Classifier: Programming Language :: Python :: 3.12
Classifier: Operating System :: OS Independent
Classifier: Intended Audience :: Science/Research
Classifier: Topic :: Scientific/Engineering :: Chemistry
Classifier: Topic :: Software Development :: Libraries :: Python Modules
Requires-Python: >=3.9
License-File: LICENSE
Requires-Dist: numpy>=1.24
Provides-Extra: dev
Requires-Dist: pytest>=7; extra == "dev"
Dynamic: license-file
